{
  "id": "558f2919-0414-45dc-853d-287b754b685a",
  "prevId": "6751ab32-f4e3-4417-bb24-9d3060582f4a",
  "version": "7",
  "dialect": "postgresql",
  "tables": {
    "public.catalog_media": {
      "name": "catalog_media",
      "schema": "",
      "columns": {
        "id": {
          "name": "id",
          "type": "uuid",
          "primaryKey": true,
          "notNull": true
        },
        "kind": {
          "name": "kind",
          "type": "text",
          "primaryKey": false,
          "notNull": true
        },
        "title": {
          "name": "title",
          "type": "text",
          "primaryKey": false,
          "notNull": true
        },
        "synonyms": {
          "name": "synonyms",
          "type": "text[]",
          "primaryKey": false,
          "notNull": true,
          "default": "'{}'"
        },
        "year": {
          "name": "year",
          "type": "integer",
          "primaryKey": false,
          "notNull": false
        },
        "status": {
          "name": "status",
          "type": "text",
          "primaryKey": false,
          "notNull": false
        },
        "genres": {
          "name": "genres",
          "type": "text[]",
          "primaryKey": false,
          "notNull": true,
          "default": "'{}'"
        },
        "episode_count": {
          "name": "episode_count",
          "type": "integer",
          "primaryKey": false,
          "notNull": false
        },
        "season_count": {
          "name": "season_count",
          "type": "integer",
          "primaryKey": false,
          "notNull": false
        },
        "chapter_count": {
          "name": "chapter_count",
          "type": "integer",
          "primaryKey": false,
          "notNull": false
        },
        "volume_count": {
          "name": "volume_count",
          "type": "integer",
          "primaryKey": false,
          "notNull": false
        },
        "external_ids": {
          "name": "external_ids",
          "type": "jsonb",
          "primaryKey": false,
          "notNull": true,
          "default": "'{}'::jsonb"
        },
        "description": {
          "name": "description",
          "type": "text",
          "primaryKey": false,
          "notNull": false
        },
        "cover_url": {
          "name": "cover_url",
          "type": "text",
          "primaryKey": false,
          "notNull": false
        },
        "seq": {
          "name": "seq",
          "type": "bigint",
          "primaryKey": false,
          "notNull": true,
          "default": 0
        },
        "deleted_at": {
          "name": "deleted_at",
          "type": "timestamp with time zone",
          "primaryKey": false,
          "notNull": false
        },
        "created_at": {
          "name": "created_at",
          "type": "timestamp with time zone",
          "primaryKey": false,
          "notNull": true,
          "default": "now()"
        },
        "updated_at": {
          "name": "updated_at",
          "type": "timestamp with time zone",
          "primaryKey": false,
          "notNull": true,
          "default": "now()"
        }
      },
      "indexes": {
        "catalog_media_seq_idx": {
          "name": "catalog_media_seq_idx",
          "columns": [
            {
              "expression": "seq",
              "isExpression": false,
              "asc": true,
              "nulls": "last"
            }
          ],
          "isUnique": false,
          "concurrently": false,
          "method": "btree",
          "with": {}
        },
        "catalog_media_kind_idx": {
          "name": "catalog_media_kind_idx",
          "columns": [
            {
              "expression": "kind",
              "isExpression": false,
              "asc": true,
              "nulls": "last"
            }
          ],
          "isUnique": false,
          "concurrently": false,
          "method": "btree",
          "with": {}
        },
        "catalog_media_title_trgm_idx": {
          "name": "catalog_media_title_trgm_idx",
          "columns": [
            {
              "expression": "\"title\" gin_trgm_ops",
              "asc": true,
              "isExpression": true,
              "nulls": "last"
            }
          ],
          "isUnique": false,
          "concurrently": false,
          "method": "gin",
          "with": {}
        }
      },
      "foreignKeys": {},
      "compositePrimaryKeys": {},
      "uniqueConstraints": {},
      "policies": {},
      "checkConstraints": {},
      "isRLSEnabled": false
    }
  },
  "enums": {},
  "schemas": {},
  "sequences": {},
  "roles": {},
  "policies": {},
  "views": {},
  "_meta": {
    "columns": {},
    "schemas": {},
    "tables": {}
  }
}